kami_uno_database/__init__.py
kami_uno_database/constants.py
kami_uno_database/database.py
kami_uno_database/functions/functions.sql
kami_uno_database/indexes/nota_fiscal_situacao_dt_emissao.sql
kami_uno_database/queries/qy_active_customers.sql
kami_uno_database/queries/qy_active_customers_contacts.sql
kami_uno_database/queries/qy_beexp_orders.sql
kami_uno_database/queries/qy_contact_sellers.sql
kami_uno_database/queries/qy_default_seller.sql
kami_uno_database/queries/qy_last_beexp_order.sql
kami_uno_database/queries/qy_participant_seller.sql
kami_uno_database/queries/qy_sales_teams.sql
kami_uno_database/queries/qy_sellers_contact.sql
kami_uno_database/scripts/functions_permissions.sql
kami_uno_database/views/vw_board_billings.sql
kami_uno_database/views/vw_customer_details.sql
kami_uno_database/views/vw_future_bills.sql
kami_uno_database/views/vw_rfv_classification.sql
kami_uno_database/views/vw_sales_invoices.sql
kami_uno_database/views/vw_sales_lines.sql
kami_uno_database-0.2.7.dist-info/LICENSE
kami_uno_database-0.2.7.dist-info/METADATA
kami_uno_database-0.2.7.dist-info/WHEEL
kami_uno_database-0.2.7.dist-info/RECORD
