Metadata-Version: 2.1
Name: kami-uno-database
Version: 0.2.7
Summary: Python Connection For Kami database instance from UNO
Author: Maicon de Menezes
Author-email: maicon@kamico.com.br
Requires-Python: >=3.10,<4.0
Classifier: Development Status :: 4 - Beta
Classifier: Natural Language :: English
Classifier: Programming Language :: Python :: 3
Classifier: Programming Language :: Python :: 3.10
Classifier: Programming Language :: Python :: 3.11
Classifier: Topic :: Database
Requires-Dist: kami-filemanager (>=0.1.0,<0.2.0)
Requires-Dist: kami-logging (>=0.2.1,<0.3.0)
Requires-Dist: pandas (>=2.1.0,<3.0.0)
Requires-Dist: pymysql (>=1.1.0,<2.0.0)
Requires-Dist: python-dotenv (>=1.0.0,<2.0.0)
Requires-Dist: sqlalchemy (>=2.0.20,<3.0.0)
Project-URL: Bug Tracker, https://github.com/devkami/kami-uno-database/issues
Project-URL: Source, https://github.com/devkami/kami-uno-database
